mobileclip/__about__.py
mobileclip/__init__.py
mobileclip/main.py
mobileclip-0.0.1.dist-info/METADATA
mobileclip-0.0.1.dist-info/WHEEL
mobileclip-0.0.1.dist-info/licenses/LICENSE.txt
mobileclip-0.0.1.dist-info/RECORD
